[{"senderKeyId":1077038465,"senderChainKey":{"iteration":165,"seed":"t2aT5VhF9IQRg5fdkh5seNXJhsnHjKOSx//jXea88g0="},"senderSigningKey":{"public":"BaQdnqeldakOHt1j7Y9tCCz0bQb80nELYgpEzceXILox","private":"iBi+JYwJ5MBAwpT750PCgcNOt0OMFmhs6x/CWjKb+lg="},"senderMessageKeys":[{},{},{},{},{},{},{},{},{},{},{},{},{},{},{},{},{},{},{},{},{},{},{},{},{},{},{},{},{},{},{},{},{},{},{},{},{},{},{},{},{},{},{},{},{},{},{},{},{},{},{},{},{},{},{},{},{},{},{},{},{},{},{},{},{},{},{},{},{},{},{},{},{},{},{},{},{},{},{},{},{},{}]}]